{
  "name": "castmydata-jsclient",
  "description": "Client for CastMyData",
  "main": "src/castmydata.js",
  "authors": [
    "Zulfa Juniadi <zulfajuniadi@gmail.com> (http://www.zulfajuniadi.com)"
  ],
  "license": "MIT",
  "homepage": "https://github.com/castmydata/castmydata-jsclient",
  "ignore": [
    "**/.*",
    "node_modules",
    "bower_components",
    "test",
    "tests"
  ],
  "dependencies": {
    "socket.io-client": "^1.4.6"
  },
  "_release": "15d13485a6",
  "_resolution": {
    "type": "branch",
    "branch": "master",
    "commit": "15d13485a66595d584acb482e81de49358ecd1a3"
  },
  "_source": "https://github.com/castmydata/castmydata-jsclient.git",
  "_target": "*",
  "_originalSource": "castmydata-jsclient",
  "_direct": true
}